{
    "63187": {
        "name": "I Suck At Fantasy HC",
        "owner": "Tmuni",
        "wins": 12,
        "losses": 2,
        "PF": 2895.5,
        "playoff_odds": 99.91,
        "seeds": [
            43.42,
            29.62,
            15.56,
            7.98,
            2.6,
            0.73,
            0.09,
            0.0,
            0.0,
            0.0,
            0.0,
            0.0,
            0.0,
            0.0
        ],
        "records": {
            "7-0": {
                "made_playoffs": 804,
                "total": 804,
                "odds": 100.0
            },
            "6-1": {
                "made_playoffs": 5478,
                "total": 5478,
                "odds": 100.0
            },
            "5-2": {
                "made_playoffs": 16345,
                "total": 16345,
                "odds": 100.0
            },
            "4-3": {
                "made_playoffs": 27583,
                "total": 27583,
                "odds": 100.0
            },
            "3-4": {
                "made_playoffs": 27214,
                "total": 27214,
                "odds": 100.0
            },
            "2-5": {
                "made_playoffs": 16255,
                "total": 16255,
                "odds": 100.0
            },
            "1-6": {
                "made_playoffs": 5476,
                "total": 5489,
                "odds": 99.76
            },
            "0-7": {
                "made_playoffs": 751,
                "total": 832,
                "odds": 90.26
            }
        },
        "current_week": {
            "win": {
                "make_playoffs": 49839,
                "total": 49840,
                "odds": 100.0
            },
            "loss": {
                "make_playoffs": 50067,
                "total": 50160,
                "odds": 99.81
            }
        },
        "PF_avg": 206.82142857142858
    },
    "63369": {
        "name": "Yourmomcantspell",
        "owner": "yourmomcantspel",
        "wins": 12,
        "losses": 2,
        "PF": 2873.6,
        "playoff_odds": 99.9,
        "seeds": [
            40.18,
            31.18,
            16.38,
            8.64,
            2.83,
            0.7,
            0.1,
            0.0,
            0.0,
            0.0,
            0.0,
            0.0,
            0.0,
            0.0
        ],
        "records": {
            "7-0": {
                "made_playoffs": 715,
                "total": 715,
                "odds": 100.0
            },
            "6-1": {
                "made_playoffs": 5398,
                "total": 5398,
                "odds": 100.0
            },
            "5-2": {
                "made_playoffs": 16428,
                "total": 16428,
                "odds": 100.0
            },
            "4-3": {
                "made_playoffs": 27203,
                "total": 27203,
                "odds": 100.0
            },
            "3-4": {
                "made_playoffs": 27230,
                "total": 27230,
                "odds": 100.0
            },
            "2-5": {
                "made_playoffs": 16544,
                "total": 16544,
                "odds": 100.0
            },
            "1-6": {
                "made_playoffs": 5657,
                "total": 5674,
                "odds": 99.7
            },
            "0-7": {
                "made_playoffs": 722,
                "total": 808,
                "odds": 89.36
            }
        },
        "current_week": {
            "win": {
                "make_playoffs": 49697,
                "total": 49701,
                "odds": 99.99
            },
            "loss": {
                "make_playoffs": 50200,
                "total": 50299,
                "odds": 99.8
            }
        },
        "PF_avg": 205.25714285714284
    },
    "63193": {
        "name": "Book Hockey",
        "owner": "TwoPlanks",
        "wins": 10,
        "losses": 4,
        "PF": 3078.4,
        "playoff_odds": 96.09,
        "seeds": [
            8.26,
            17.46,
            25.04,
            22.68,
            14.73,
            7.93,
            3.21,
            0.6,
            0.1,
            0.0,
            0.0,
            0.0,
            0.0,
            0.0
        ],
        "records": {
            "7-0": {
                "made_playoffs": 747,
                "total": 747,
                "odds": 100.0
            },
            "6-1": {
                "made_playoffs": 5458,
                "total": 5458,
                "odds": 100.0
            },
            "5-2": {
                "made_playoffs": 16331,
                "total": 16331,
                "odds": 100.0
            },
            "4-3": {
                "made_playoffs": 27077,
                "total": 27077,
                "odds": 100.0
            },
            "3-4": {
                "made_playoffs": 27390,
                "total": 27399,
                "odds": 99.97
            },
            "2-5": {
                "made_playoffs": 15986,
                "total": 16701,
                "odds": 95.72
            },
            "1-6": {
                "made_playoffs": 3052,
                "total": 5525,
                "odds": 55.24
            },
            "0-7": {
                "made_playoffs": 53,
                "total": 762,
                "odds": 6.96
            }
        },
        "current_week": {
            "win": {
                "make_playoffs": 49299,
                "total": 49919,
                "odds": 98.76
            },
            "loss": {
                "make_playoffs": 46795,
                "total": 50081,
                "odds": 93.44
            }
        },
        "PF_avg": 219.8857142857143
    },
    "63216": {
        "name": "Bluth's Bananas",
        "owner": "zodiac33",
        "wins": 10,
        "losses": 4,
        "PF": 2997.8,
        "playoff_odds": 95.38,
        "seeds": [
            7.07,
            15.5,
            23.48,
            24.37,
            16.03,
            8.93,
            3.8,
            0.69,
            0.12,
            0.01,
            0.0,
            0.0,
            0.0,
            0.0
        ],
        "records": {
            "7-0": {
                "made_playoffs": 793,
                "total": 793,
                "odds": 100.0
            },
            "6-1": {
                "made_playoffs": 5553,
                "total": 5553,
                "odds": 100.0
            },
            "5-2": {
                "made_playoffs": 16406,
                "total": 16406,
                "odds": 100.0
            },
            "4-3": {
                "made_playoffs": 27689,
                "total": 27689,
                "odds": 100.0
            },
            "3-4": {
                "made_playoffs": 27217,
                "total": 27237,
                "odds": 99.93
            },
            "2-5": {
                "made_playoffs": 15164,
                "total": 16217,
                "odds": 93.51
            },
            "1-6": {
                "made_playoffs": 2529,
                "total": 5328,
                "odds": 47.47
            },
            "0-7": {
                "made_playoffs": 30,
                "total": 777,
                "odds": 3.86
            }
        },
        "current_week": {
            "win": {
                "make_playoffs": 49216,
                "total": 50062,
                "odds": 98.31
            },
            "loss": {
                "make_playoffs": 46165,
                "total": 49938,
                "odds": 92.44
            }
        },
        "PF_avg": 214.12857142857143
    },
    "63208": {
        "name": "Kuznetsob",
        "owner": "kuznetsob",
        "wins": 9,
        "losses": 5,
        "PF": 2773.6,
        "playoff_odds": 76.44,
        "seeds": [
            0.64,
            3.09,
            7.99,
            14.87,
            24.79,
            25.07,
            17.57,
            4.49,
            1.2,
            0.26,
            0.03,
            0.0,
            0.0,
            0.0
        ],
        "records": {
            "7-0": {
                "made_playoffs": 730,
                "total": 730,
                "odds": 100.0
            },
            "6-1": {
                "made_playoffs": 5549,
                "total": 5549,
                "odds": 100.0
            },
            "5-2": {
                "made_playoffs": 16379,
                "total": 16380,
                "odds": 99.99
            },
            "4-3": {
                "made_playoffs": 27026,
                "total": 27452,
                "odds": 98.45
            },
            "3-4": {
                "made_playoffs": 21302,
                "total": 27304,
                "odds": 78.02
            },
            "2-5": {
                "made_playoffs": 5222,
                "total": 16320,
                "odds": 32.0
            },
            "1-6": {
                "made_playoffs": 234,
                "total": 5512,
                "odds": 4.25
            },
            "0-7": {
                "made_playoffs": 0,
                "total": 753,
                "odds": 0.0
            }
        },
        "current_week": {
            "win": {
                "make_playoffs": 43085,
                "total": 50160,
                "odds": 85.9
            },
            "loss": {
                "make_playoffs": 33357,
                "total": 49840,
                "odds": 66.93
            }
        },
        "PF_avg": 198.1142857142857
    },
    "63270": {
        "name": "Waddell In to the Wild Card Spot",
        "owner": "Oldmanfreeman",
        "wins": 9,
        "losses": 5,
        "PF": 2713.65,
        "playoff_odds": 70.42,
        "seeds": [
            0.34,
            2.42,
            8.43,
            13.94,
            21.27,
            24.02,
            21.08,
            6.17,
            1.85,
            0.43,
            0.04,
            0.0,
            0.0,
            0.0
        ],
        "records": {
            "7-0": {
                "made_playoffs": 835,
                "total": 835,
                "odds": 100.0
            },
            "6-1": {
                "made_playoffs": 5421,
                "total": 5421,
                "odds": 100.0
            },
            "5-2": {
                "made_playoffs": 16487,
                "total": 16491,
                "odds": 99.98
            },
            "4-3": {
                "made_playoffs": 26367,
                "total": 27292,
                "odds": 96.61
            },
            "3-4": {
                "made_playoffs": 18152,
                "total": 27314,
                "odds": 66.46
            },
            "2-5": {
                "made_playoffs": 3103,
                "total": 16351,
                "odds": 18.98
            },
            "1-6": {
                "made_playoffs": 58,
                "total": 5462,
                "odds": 1.06
            },
            "0-7": {
                "made_playoffs": 0,
                "total": 834,
                "odds": 0.0
            }
        },
        "current_week": {
            "win": {
                "make_playoffs": 40112,
                "total": 49784,
                "odds": 80.57
            },
            "loss": {
                "make_playoffs": 30311,
                "total": 50216,
                "odds": 60.36
            }
        },
        "PF_avg": 193.83214285714286
    },
    "63347": {
        "name": "Hamburgergaming76",
        "owner": "Mac1125",
        "wins": 8,
        "losses": 6,
        "PF": 2841.85,
        "playoff_odds": 52.78,
        "seeds": [
            0.09,
            0.73,
            3.09,
            7.26,
            16.04,
            25.58,
            29.91,
            11.17,
            4.37,
            1.43,
            0.3,
            0.03,
            0.0,
            0.0
        ],
        "records": {
            "7-0": {
                "made_playoffs": 765,
                "total": 765,
                "odds": 100.0
            },
            "6-1": {
                "made_playoffs": 5420,
                "total": 5421,
                "odds": 99.98
            },
            "5-2": {
                "made_playoffs": 16158,
                "total": 16394,
                "odds": 98.56
            },
            "4-3": {
                "made_playoffs": 21489,
                "total": 27633,
                "odds": 77.77
            },
            "3-4": {
                "made_playoffs": 8426,
                "total": 27426,
                "odds": 30.72
            },
            "2-5": {
                "made_playoffs": 525,
                "total": 16191,
                "odds": 3.24
            },
            "1-6": {
                "made_playoffs": 2,
                "total": 5398,
                "odds": 0.04
            },
            "0-7": {
                "made_playoffs": 0,
                "total": 772,
                "odds": 0.0
            }
        },
        "current_week": {
            "win": {
                "make_playoffs": 32571,
                "total": 50089,
                "odds": 65.03
            },
            "loss": {
                "make_playoffs": 20214,
                "total": 49911,
                "odds": 40.5
            }
        },
        "PF_avg": 202.9892857142857
    },
    "63594": {
        "name": "Dumplers",
        "owner": "ShinyLeprechaun",
        "wins": 6,
        "losses": 8,
        "PF": 2727.0,
        "playoff_odds": 4.67,
        "seeds": [
            0.0,
            0.0,
            0.02,
            0.17,
            0.9,
            3.59,
            10.82,
            29.23,
            26.11,
            16.71,
            8.76,
            3.34,
            0.36,
            0.0
        ],
        "records": {
            "7-0": {
                "made_playoffs": 723,
                "total": 779,
                "odds": 92.81
            },
            "6-1": {
                "made_playoffs": 2622,
                "total": 5504,
                "odds": 47.64
            },
            "5-2": {
                "made_playoffs": 1235,
                "total": 16417,
                "odds": 7.52
            },
            "4-3": {
                "made_playoffs": 90,
                "total": 27204,
                "odds": 0.33
            },
            "3-4": {
                "made_playoffs": 0,
                "total": 27502,
                "odds": 0.0
            },
            "2-5": {
                "made_playoffs": 0,
                "total": 16456,
                "odds": 0.0
            },
            "1-6": {
                "made_playoffs": 0,
                "total": 5303,
                "odds": 0.0
            },
            "0-7": {
                "made_playoffs": 0,
                "total": 835,
                "odds": 0.0
            }
        },
        "current_week": {
            "win": {
                "make_playoffs": 3908,
                "total": 50081,
                "odds": 7.8
            },
            "loss": {
                "make_playoffs": 762,
                "total": 49919,
                "odds": 1.53
            }
        },
        "PF_avg": 194.78571428571428
    },
    "63209": {
        "name": "Dolla Bill Kirill",
        "owner": "CTonyJab",
        "wins": 6,
        "losses": 8,
        "PF": 2617.65,
        "playoff_odds": 3.06,
        "seeds": [
            0.0,
            0.0,
            0.01,
            0.1,
            0.65,
            2.3,
            7.98,
            24.27,
            25.62,
            20.18,
            12.66,
            5.75,
            0.48,
            0.0
        ],
        "records": {
            "7-0": {
                "made_playoffs": 723,
                "total": 808,
                "odds": 89.48
            },
            "6-1": {
                "made_playoffs": 1855,
                "total": 5424,
                "odds": 34.2
            },
            "5-2": {
                "made_playoffs": 469,
                "total": 16403,
                "odds": 2.86
            },
            "4-3": {
                "made_playoffs": 13,
                "total": 27173,
                "odds": 0.05
            },
            "3-4": {
                "made_playoffs": 0,
                "total": 27346,
                "odds": 0.0
            },
            "2-5": {
                "made_playoffs": 0,
                "total": 16508,
                "odds": 0.0
            },
            "1-6": {
                "made_playoffs": 0,
                "total": 5577,
                "odds": 0.0
            },
            "0-7": {
                "made_playoffs": 0,
                "total": 761,
                "odds": 0.0
            }
        },
        "current_week": {
            "win": {
                "make_playoffs": 2613,
                "total": 50299,
                "odds": 5.19
            },
            "loss": {
                "make_playoffs": 447,
                "total": 49701,
                "odds": 0.9
            }
        },
        "PF_avg": 186.975
    },
    "63285": {
        "name": "Moves Like Jagr",
        "owner": "Moves_Like_Jagr",
        "wins": 5,
        "losses": 9,
        "PF": 2699.1,
        "playoff_odds": 0.86,
        "seeds": [
            0.0,
            0.0,
            0.0,
            0.0,
            0.13,
            0.73,
            3.1,
            13.12,
            20.12,
            25.49,
            23.16,
            12.48,
            1.63,
            0.04
        ],
        "records": {
            "7-0": {
                "made_playoffs": 414,
                "total": 815,
                "odds": 50.8
            },
            "6-1": {
                "made_playoffs": 413,
                "total": 5334,
                "odds": 7.74
            },
            "5-2": {
                "made_playoffs": 33,
                "total": 16483,
                "odds": 0.2
            },
            "4-3": {
                "made_playoffs": 0,
                "total": 27342,
                "odds": 0.0
            },
            "3-4": {
                "made_playoffs": 0,
                "total": 27469,
                "odds": 0.0
            },
            "2-5": {
                "made_playoffs": 0,
                "total": 16265,
                "odds": 0.0
            },
            "1-6": {
                "made_playoffs": 0,
                "total": 5461,
                "odds": 0.0
            },
            "0-7": {
                "made_playoffs": 0,
                "total": 831,
                "odds": 0.0
            }
        },
        "current_week": {
            "win": {
                "make_playoffs": 816,
                "total": 50216,
                "odds": 1.62
            },
            "loss": {
                "make_playoffs": 44,
                "total": 49784,
                "odds": 0.09
            }
        },
        "PF_avg": 192.79285714285714
    },
    "63225": {
        "name": "ZavCongratz",
        "owner": "mii817",
        "wins": 5,
        "losses": 9,
        "PF": 2261.3,
        "playoff_odds": 0.47,
        "seeds": [
            0.0,
            0.0,
            0.0,
            0.0,
            0.04,
            0.42,
            2.02,
            7.27,
            13.22,
            20.61,
            25.9,
            26.75,
            3.7,
            0.07
        ],
        "records": {
            "7-0": {
                "made_playoffs": 317,
                "total": 806,
                "odds": 39.33
            },
            "6-1": {
                "made_playoffs": 149,
                "total": 5451,
                "odds": 2.73
            },
            "5-2": {
                "made_playoffs": 3,
                "total": 16498,
                "odds": 0.02
            },
            "4-3": {
                "made_playoffs": 0,
                "total": 27246,
                "odds": 0.0
            },
            "3-4": {
                "made_playoffs": 0,
                "total": 27442,
                "odds": 0.0
            },
            "2-5": {
                "made_playoffs": 0,
                "total": 16285,
                "odds": 0.0
            },
            "1-6": {
                "made_playoffs": 0,
                "total": 5474,
                "odds": 0.0
            },
            "0-7": {
                "made_playoffs": 0,
                "total": 798,
                "odds": 0.0
            }
        },
        "current_week": {
            "win": {
                "make_playoffs": 455,
                "total": 49911,
                "odds": 0.91
            },
            "loss": {
                "make_playoffs": 14,
                "total": 50089,
                "odds": 0.03
            }
        },
        "PF_avg": 161.52142857142857
    },
    "63350": {
        "name": "Five Tool to the Five Hole",
        "owner": "TheAndyRichter",
        "wins": 4,
        "losses": 10,
        "PF": 2573.25,
        "playoff_odds": 0.01,
        "seeds": [
            0.0,
            0.0,
            0.0,
            0.0,
            0.0,
            0.01,
            0.32,
            2.96,
            7.16,
            14.2,
            26.2,
            39.15,
            9.65,
            0.34
        ],
        "records": {
            "7-0": {
                "made_playoffs": 12,
                "total": 759,
                "odds": 1.58
            },
            "6-1": {
                "made_playoffs": 1,
                "total": 5680,
                "odds": 0.02
            },
            "5-2": {
                "made_playoffs": 0,
                "total": 16458,
                "odds": 0.0
            },
            "4-3": {
                "made_playoffs": 0,
                "total": 27157,
                "odds": 0.0
            },
            "3-4": {
                "made_playoffs": 0,
                "total": 27135,
                "odds": 0.0
            },
            "2-5": {
                "made_playoffs": 0,
                "total": 16508,
                "odds": 0.0
            },
            "1-6": {
                "made_playoffs": 0,
                "total": 5513,
                "odds": 0.0
            },
            "0-7": {
                "made_playoffs": 0,
                "total": 790,
                "odds": 0.0
            }
        },
        "current_week": {
            "win": {
                "make_playoffs": 13,
                "total": 49938,
                "odds": 0.03
            },
            "loss": {
                "make_playoffs": 0,
                "total": 50062,
                "odds": 0.0
            }
        },
        "PF_avg": 183.80357142857142
    },
    "63406": {
        "name": "Straight Cash Homie",
        "owner": "hockeymax93",
        "wins": 2,
        "losses": 12,
        "PF": 2220.85,
        "playoff_odds": 0.0,
        "seeds": [
            0.0,
            0.0,
            0.0,
            0.0,
            0.0,
            0.0,
            0.0,
            0.02,
            0.13,
            0.68,
            2.9,
            11.9,
            72.35,
            12.02
        ],
        "records": {
            "7-0": {
                "made_playoffs": 0,
                "total": 747,
                "odds": 0.0
            },
            "6-1": {
                "made_playoffs": 0,
                "total": 5579,
                "odds": 0.0
            },
            "5-2": {
                "made_playoffs": 0,
                "total": 16307,
                "odds": 0.0
            },
            "4-3": {
                "made_playoffs": 0,
                "total": 27589,
                "odds": 0.0
            },
            "3-4": {
                "made_playoffs": 0,
                "total": 27196,
                "odds": 0.0
            },
            "2-5": {
                "made_playoffs": 0,
                "total": 16408,
                "odds": 0.0
            },
            "1-6": {
                "made_playoffs": 0,
                "total": 5439,
                "odds": 0.0
            },
            "0-7": {
                "made_playoffs": 0,
                "total": 735,
                "odds": 0.0
            }
        },
        "current_week": {
            "win": {
                "make_playoffs": 0,
                "total": 50316,
                "odds": 0.0
            },
            "loss": {
                "make_playoffs": 0,
                "total": 49684,
                "odds": 0.0
            }
        },
        "PF_avg": 158.63214285714284
    },
    "63195": {
        "name": "Deep Shame",
        "owner": "PlainGuy1018",
        "wins": 0,
        "losses": 14,
        "PF": 2100.45,
        "playoff_odds": 0.0,
        "seeds": [
            0.0,
            0.0,
            0.0,
            0.0,
            0.0,
            0.0,
            0.0,
            0.0,
            0.0,
            0.0,
            0.04,
            0.6,
            11.83,
            87.53
        ],
        "records": {
            "7-0": {
                "made_playoffs": 0,
                "total": 807,
                "odds": 0.0
            },
            "6-1": {
                "made_playoffs": 0,
                "total": 5435,
                "odds": 0.0
            },
            "5-2": {
                "made_playoffs": 0,
                "total": 16420,
                "odds": 0.0
            },
            "4-3": {
                "made_playoffs": 0,
                "total": 27192,
                "odds": 0.0
            },
            "3-4": {
                "made_playoffs": 0,
                "total": 27250,
                "odds": 0.0
            },
            "2-5": {
                "made_playoffs": 0,
                "total": 16669,
                "odds": 0.0
            },
            "1-6": {
                "made_playoffs": 0,
                "total": 5484,
                "odds": 0.0
            },
            "0-7": {
                "made_playoffs": 0,
                "total": 743,
                "odds": 0.0
            }
        },
        "current_week": {
            "win": {
                "make_playoffs": 0,
                "total": 49684,
                "odds": 0.0
            },
            "loss": {
                "make_playoffs": 0,
                "total": 50316,
                "odds": 0.0
            }
        },
        "PF_avg": 150.03214285714284
    }
}