{
    "63399": {
        "name": "Hayzer",
        "owner": "Hayzer13",
        "wins": 14,
        "losses": 3,
        "PF": 3846.15,
        "playoff_odds": 100.0,
        "seeds": [
            49.73,
            38.28,
            9.9,
            2.03,
            0.06,
            0.0,
            0.0,
            0.0,
            0.0,
            0.0,
            0.0,
            0.0,
            0.0,
            0.0
        ],
        "records": {
            "4-0": {
                "made_playoffs": 6137,
                "total": 6137,
                "odds": 100.0
            },
            "3-1": {
                "made_playoffs": 25036,
                "total": 25036,
                "odds": 100.0
            },
            "2-2": {
                "made_playoffs": 37586,
                "total": 37586,
                "odds": 100.0
            },
            "1-3": {
                "made_playoffs": 24988,
                "total": 24988,
                "odds": 100.0
            },
            "0-4": {
                "made_playoffs": 6253,
                "total": 6253,
                "odds": 100.0
            }
        },
        "current_week": {
            "win": {
                "make_playoffs": 49823,
                "total": 49823,
                "odds": 100.0
            },
            "loss": {
                "make_playoffs": 50177,
                "total": 50177,
                "odds": 100.0
            }
        },
        "PF_avg": 226.24411764705883
    },
    "63357": {
        "name": "Cats & Rats",
        "owner": "aisf",
        "wins": 14,
        "losses": 3,
        "PF": 3805.7,
        "playoff_odds": 100.0,
        "seeds": [
            42.81,
            40.67,
            13.98,
            2.48,
            0.05,
            0.0,
            0.0,
            0.0,
            0.0,
            0.0,
            0.0,
            0.0,
            0.0,
            0.0
        ],
        "records": {
            "4-0": {
                "made_playoffs": 6301,
                "total": 6301,
                "odds": 100.0
            },
            "3-1": {
                "made_playoffs": 24932,
                "total": 24932,
                "odds": 100.0
            },
            "2-2": {
                "made_playoffs": 37511,
                "total": 37511,
                "odds": 100.0
            },
            "1-3": {
                "made_playoffs": 24960,
                "total": 24960,
                "odds": 100.0
            },
            "0-4": {
                "made_playoffs": 6296,
                "total": 6296,
                "odds": 100.0
            }
        },
        "current_week": {
            "win": {
                "make_playoffs": 49863,
                "total": 49863,
                "odds": 100.0
            },
            "loss": {
                "make_playoffs": 50137,
                "total": 50137,
                "odds": 100.0
            }
        },
        "PF_avg": 223.86470588235292
    },
    "63253": {
        "name": "Beer Belly 69ers",
        "owner": "Chutchy",
        "wins": 13,
        "losses": 4,
        "PF": 3345.55,
        "playoff_odds": 100.0,
        "seeds": [
            7.06,
            17.61,
            53.28,
            18.04,
            3.56,
            0.46,
            0.0,
            0.0,
            0.0,
            0.0,
            0.0,
            0.0,
            0.0,
            0.0
        ],
        "records": {
            "4-0": {
                "made_playoffs": 6273,
                "total": 6273,
                "odds": 100.0
            },
            "3-1": {
                "made_playoffs": 24784,
                "total": 24784,
                "odds": 100.0
            },
            "2-2": {
                "made_playoffs": 37531,
                "total": 37531,
                "odds": 100.0
            },
            "1-3": {
                "made_playoffs": 25254,
                "total": 25254,
                "odds": 100.0
            },
            "0-4": {
                "made_playoffs": 6158,
                "total": 6158,
                "odds": 100.0
            }
        },
        "current_week": {
            "win": {
                "make_playoffs": 50137,
                "total": 50137,
                "odds": 100.0
            },
            "loss": {
                "make_playoffs": 49863,
                "total": 49863,
                "odds": 100.0
            }
        },
        "PF_avg": 196.79705882352943
    },
    "63281": {
        "name": "Out With The Broz",
        "owner": "morkle",
        "wins": 12,
        "losses": 5,
        "PF": 3234.85,
        "playoff_odds": 100.0,
        "seeds": [
            0.39,
            2.96,
            15.72,
            43.78,
            27.27,
            9.88,
            0.0,
            0.0,
            0.0,
            0.0,
            0.0,
            0.0,
            0.0,
            0.0
        ],
        "records": {
            "4-0": {
                "made_playoffs": 6360,
                "total": 6360,
                "odds": 100.0
            },
            "3-1": {
                "made_playoffs": 24998,
                "total": 24998,
                "odds": 100.0
            },
            "2-2": {
                "made_playoffs": 37388,
                "total": 37388,
                "odds": 100.0
            },
            "1-3": {
                "made_playoffs": 24965,
                "total": 24965,
                "odds": 100.0
            },
            "0-4": {
                "made_playoffs": 6289,
                "total": 6289,
                "odds": 100.0
            }
        },
        "current_week": {
            "win": {
                "make_playoffs": 49929,
                "total": 49929,
                "odds": 100.0
            },
            "loss": {
                "make_playoffs": 50071,
                "total": 50071,
                "odds": 100.0
            }
        },
        "PF_avg": 190.28529411764706
    },
    "63288": {
        "name": "Burning Steel",
        "owner": "staph",
        "wins": 11,
        "losses": 6,
        "PF": 3322.8,
        "playoff_odds": 99.09,
        "seeds": [
            0.01,
            0.48,
            6.22,
            26.5,
            40.9,
            24.99,
            0.88,
            0.03,
            0.0,
            0.0,
            0.0,
            0.0,
            0.0,
            0.0
        ],
        "records": {
            "4-0": {
                "made_playoffs": 6283,
                "total": 6283,
                "odds": 100.0
            },
            "3-1": {
                "made_playoffs": 24822,
                "total": 24822,
                "odds": 100.0
            },
            "2-2": {
                "made_playoffs": 37743,
                "total": 37743,
                "odds": 100.0
            },
            "1-3": {
                "made_playoffs": 24835,
                "total": 24835,
                "odds": 100.0
            },
            "0-4": {
                "made_playoffs": 5406,
                "total": 6317,
                "odds": 85.58
            }
        },
        "current_week": {
            "win": {
                "make_playoffs": 50097,
                "total": 50097,
                "odds": 100.0
            },
            "loss": {
                "make_playoffs": 48992,
                "total": 49903,
                "odds": 98.17
            }
        },
        "PF_avg": 195.45882352941177
    },
    "63272": {
        "name": "Sher-wood like the Stanley Cup",
        "owner": "okmed",
        "wins": 10,
        "losses": 7,
        "PF": 3365.55,
        "playoff_odds": 92.05,
        "seeds": [
            0.0,
            0.0,
            0.9,
            7.17,
            27.67,
            56.31,
            6.46,
            1.34,
            0.15,
            0.0,
            0.0,
            0.0,
            0.0,
            0.0
        ],
        "records": {
            "4-0": {
                "made_playoffs": 6228,
                "total": 6228,
                "odds": 100.0
            },
            "3-1": {
                "made_playoffs": 24889,
                "total": 24889,
                "odds": 100.0
            },
            "2-2": {
                "made_playoffs": 37453,
                "total": 37453,
                "odds": 100.0
            },
            "1-3": {
                "made_playoffs": 21654,
                "total": 25163,
                "odds": 86.05
            },
            "0-4": {
                "made_playoffs": 1827,
                "total": 6267,
                "odds": 29.15
            }
        },
        "current_week": {
            "win": {
                "make_playoffs": 48919,
                "total": 49982,
                "odds": 97.87
            },
            "loss": {
                "make_playoffs": 43132,
                "total": 50018,
                "odds": 86.23
            }
        },
        "PF_avg": 197.97352941176473
    },
    "63258": {
        "name": "Stinkus HC",
        "owner": "stinkus1",
        "wins": 8,
        "losses": 9,
        "PF": 2942.45,
        "playoff_odds": 3.36,
        "seeds": [
            0.0,
            0.0,
            0.0,
            0.0,
            0.12,
            3.23,
            49.52,
            31.68,
            11.77,
            3.38,
            0.29,
            0.0,
            0.0,
            0.0
        ],
        "records": {
            "4-0": {
                "made_playoffs": 2118,
                "total": 6209,
                "odds": 34.11
            },
            "3-1": {
                "made_playoffs": 1239,
                "total": 25097,
                "odds": 4.94
            },
            "2-2": {
                "made_playoffs": 0,
                "total": 37555,
                "odds": 0.0
            },
            "1-3": {
                "made_playoffs": 0,
                "total": 24898,
                "odds": 0.0
            },
            "0-4": {
                "made_playoffs": 0,
                "total": 6241,
                "odds": 0.0
            }
        },
        "current_week": {
            "win": {
                "make_playoffs": 3048,
                "total": 49936,
                "odds": 6.1
            },
            "loss": {
                "make_playoffs": 309,
                "total": 50064,
                "odds": 0.62
            }
        },
        "PF_avg": 173.08529411764704
    },
    "63314": {
        "name": "Halifax Ham Slammers",
        "owner": "Scosakel",
        "wins": 8,
        "losses": 9,
        "PF": 2872.45,
        "playoff_odds": 5.14,
        "seeds": [
            0.0,
            0.0,
            0.0,
            0.0,
            0.37,
            4.77,
            33.78,
            40.3,
            16.93,
            3.69,
            0.15,
            0.0,
            0.0,
            0.0
        ],
        "records": {
            "4-0": {
                "made_playoffs": 3431,
                "total": 6262,
                "odds": 54.79
            },
            "3-1": {
                "made_playoffs": 1709,
                "total": 25066,
                "odds": 6.82
            },
            "2-2": {
                "made_playoffs": 0,
                "total": 37624,
                "odds": 0.0
            },
            "1-3": {
                "made_playoffs": 0,
                "total": 24754,
                "odds": 0.0
            },
            "0-4": {
                "made_playoffs": 0,
                "total": 6294,
                "odds": 0.0
            }
        },
        "current_week": {
            "win": {
                "make_playoffs": 4573,
                "total": 50071,
                "odds": 9.13
            },
            "loss": {
                "make_playoffs": 567,
                "total": 49929,
                "odds": 1.14
            }
        },
        "PF_avg": 168.96764705882353
    },
    "63434": {
        "name": "Lone Wolf",
        "owner": "Medvedd",
        "wins": 7,
        "losses": 10,
        "PF": 2834.75,
        "playoff_odds": 0.36,
        "seeds": [
            0.0,
            0.0,
            0.0,
            0.0,
            0.0,
            0.36,
            7.87,
            20.26,
            47.81,
            20.47,
            2.88,
            0.32,
            0.01,
            0.0
        ],
        "records": {
            "4-0": {
                "made_playoffs": 363,
                "total": 6295,
                "odds": 5.77
            },
            "3-1": {
                "made_playoffs": 0,
                "total": 24960,
                "odds": 0.0
            },
            "2-2": {
                "made_playoffs": 0,
                "total": 37672,
                "odds": 0.0
            },
            "1-3": {
                "made_playoffs": 0,
                "total": 24941,
                "odds": 0.0
            },
            "0-4": {
                "made_playoffs": 0,
                "total": 6132,
                "odds": 0.0
            }
        },
        "current_week": {
            "win": {
                "make_playoffs": 363,
                "total": 50082,
                "odds": 0.72
            },
            "loss": {
                "make_playoffs": 0,
                "total": 49918,
                "odds": 0.0
            }
        },
        "PF_avg": 166.75
    },
    "63342": {
        "name": "Mad Teeth HC",
        "owner": "MadTeeth",
        "wins": 6,
        "losses": 11,
        "PF": 2824.55,
        "playoff_odds": 0.0,
        "seeds": [
            0.0,
            0.0,
            0.0,
            0.0,
            0.0,
            0.0,
            1.49,
            6.14,
            20.53,
            52.01,
            13.89,
            4.71,
            1.17,
            0.06
        ],
        "records": {
            "4-0": {
                "made_playoffs": 0,
                "total": 6367,
                "odds": 0.0
            },
            "3-1": {
                "made_playoffs": 0,
                "total": 25143,
                "odds": 0.0
            },
            "2-2": {
                "made_playoffs": 0,
                "total": 37376,
                "odds": 0.0
            },
            "1-3": {
                "made_playoffs": 0,
                "total": 24848,
                "odds": 0.0
            },
            "0-4": {
                "made_playoffs": 0,
                "total": 6266,
                "odds": 0.0
            }
        },
        "current_week": {
            "win": {
                "make_playoffs": 0,
                "total": 50064,
                "odds": 0.0
            },
            "loss": {
                "make_playoffs": 0,
                "total": 49936,
                "odds": 0.0
            }
        },
        "PF_avg": 166.15
    },
    "63321": {
        "name": "Capital Region Empire",
        "owner": "ShiningGrey",
        "wins": 5,
        "losses": 12,
        "PF": 2651.2,
        "playoff_odds": 0.0,
        "seeds": [
            0.0,
            0.0,
            0.0,
            0.0,
            0.0,
            0.0,
            0.01,
            0.24,
            2.32,
            12.69,
            44.1,
            25.54,
            12.03,
            3.08
        ],
        "records": {
            "4-0": {
                "made_playoffs": 0,
                "total": 6285,
                "odds": 0.0
            },
            "3-1": {
                "made_playoffs": 0,
                "total": 25009,
                "odds": 0.0
            },
            "2-2": {
                "made_playoffs": 0,
                "total": 37102,
                "odds": 0.0
            },
            "1-3": {
                "made_playoffs": 0,
                "total": 25194,
                "odds": 0.0
            },
            "0-4": {
                "made_playoffs": 0,
                "total": 6410,
                "odds": 0.0
            }
        },
        "current_week": {
            "win": {
                "make_playoffs": 0,
                "total": 50018,
                "odds": 0.0
            },
            "loss": {
                "make_playoffs": 0,
                "total": 49982,
                "odds": 0.0
            }
        },
        "PF_avg": 155.95294117647057
    },
    "63274": {
        "name": "Bench Warmers",
        "owner": "Vadin",
        "wins": 4,
        "losses": 13,
        "PF": 2724.2,
        "playoff_odds": 0.0,
        "seeds": [
            0.0,
            0.0,
            0.0,
            0.0,
            0.0,
            0.0,
            0.0,
            0.0,
            0.34,
            4.97,
            20.61,
            28.39,
            27.14,
            18.55
        ],
        "records": {
            "4-0": {
                "made_playoffs": 0,
                "total": 6167,
                "odds": 0.0
            },
            "3-1": {
                "made_playoffs": 0,
                "total": 24978,
                "odds": 0.0
            },
            "2-2": {
                "made_playoffs": 0,
                "total": 37659,
                "odds": 0.0
            },
            "1-3": {
                "made_playoffs": 0,
                "total": 24951,
                "odds": 0.0
            },
            "0-4": {
                "made_playoffs": 0,
                "total": 6245,
                "odds": 0.0
            }
        },
        "current_week": {
            "win": {
                "make_playoffs": 0,
                "total": 49903,
                "odds": 0.0
            },
            "loss": {
                "make_playoffs": 0,
                "total": 50097,
                "odds": 0.0
            }
        },
        "PF_avg": 160.24705882352941
    },
    "63416": {
        "name": "Chuk & Chuk for the people",
        "owner": "SaventMelody",
        "wins": 4,
        "losses": 13,
        "PF": 2339.7,
        "playoff_odds": 0.0,
        "seeds": [
            0.0,
            0.0,
            0.0,
            0.0,
            0.0,
            0.0,
            0.0,
            0.0,
            0.09,
            1.77,
            10.58,
            24.35,
            30.8,
            32.41
        ],
        "records": {
            "4-0": {
                "made_playoffs": 0,
                "total": 6189,
                "odds": 0.0
            },
            "3-1": {
                "made_playoffs": 0,
                "total": 25244,
                "odds": 0.0
            },
            "2-2": {
                "made_playoffs": 0,
                "total": 37222,
                "odds": 0.0
            },
            "1-3": {
                "made_playoffs": 0,
                "total": 25041,
                "odds": 0.0
            },
            "0-4": {
                "made_playoffs": 0,
                "total": 6304,
                "odds": 0.0
            }
        },
        "current_week": {
            "win": {
                "make_playoffs": 0,
                "total": 50177,
                "odds": 0.0
            },
            "loss": {
                "make_playoffs": 0,
                "total": 49823,
                "odds": 0.0
            }
        },
        "PF_avg": 137.62941176470588
    },
    "63372": {
        "name": "London Divers",
        "owner": "amaccc",
        "wins": 3,
        "losses": 14,
        "PF": 2838.8,
        "playoff_odds": 0.0,
        "seeds": [
            0.0,
            0.0,
            0.0,
            0.0,
            0.0,
            0.0,
            0.0,
            0.0,
            0.07,
            1.01,
            7.49,
            16.69,
            28.84,
            45.9
        ],
        "records": {
            "4-0": {
                "made_playoffs": 0,
                "total": 6112,
                "odds": 0.0
            },
            "3-1": {
                "made_playoffs": 0,
                "total": 25066,
                "odds": 0.0
            },
            "2-2": {
                "made_playoffs": 0,
                "total": 37830,
                "odds": 0.0
            },
            "1-3": {
                "made_playoffs": 0,
                "total": 24760,
                "odds": 0.0
            },
            "0-4": {
                "made_playoffs": 0,
                "total": 6232,
                "odds": 0.0
            }
        },
        "current_week": {
            "win": {
                "make_playoffs": 0,
                "total": 49918,
                "odds": 0.0
            },
            "loss": {
                "make_playoffs": 0,
                "total": 50082,
                "odds": 0.0
            }
        },
        "PF_avg": 166.98823529411766
    }
}