{
    "63163": {
        "name": "Mackstreet Boys",
        "owner": "TheRealClaude",
        "wins": 7,
        "losses": 2,
        "PF": 2106.55,
        "playoff_odds": 99.72,
        "seeds": [
            77.2,
            13.93,
            5.02,
            2.2,
            0.96,
            0.41,
            0.19,
            0.06,
            0.02,
            0.01,
            0.0,
            0.0,
            0.0,
            0.0
        ],
        "records": {
            "12-0": {
                "made_playoffs": 1761,
                "total": 1761,
                "odds": 100.0
            },
            "11-1": {
                "made_playoffs": 8322,
                "total": 8322,
                "odds": 100.0
            },
            "10-2": {
                "made_playoffs": 18353,
                "total": 18353,
                "odds": 100.0
            },
            "9-3": {
                "made_playoffs": 24959,
                "total": 24959,
                "odds": 100.0
            },
            "8-4": {
                "made_playoffs": 22576,
                "total": 22576,
                "odds": 100.0
            },
            "7-5": {
                "made_playoffs": 14356,
                "total": 14356,
                "odds": 100.0
            },
            "6-6": {
                "made_playoffs": 6716,
                "total": 6716,
                "odds": 100.0
            },
            "5-7": {
                "made_playoffs": 2294,
                "total": 2311,
                "odds": 99.26
            },
            "4-8": {
                "made_playoffs": 369,
                "total": 531,
                "odds": 69.49
            },
            "3-9": {
                "made_playoffs": 18,
                "total": 97,
                "odds": 18.56
            },
            "2-10": {
                "made_playoffs": 0,
                "total": 16,
                "odds": 0.0
            },
            "1-11": {
                "made_playoffs": 0,
                "total": 2,
                "odds": 0.0
            }
        },
        "current_week": {
            "win": {
                "make_playoffs": 77690,
                "total": 77791,
                "odds": 99.87
            },
            "loss": {
                "make_playoffs": 22034,
                "total": 22209,
                "odds": 99.21
            }
        },
        "PF_avg": 234.06111111111113
    },
    "63145": {
        "name": "Bong Horvat",
        "owner": "Haychan",
        "wins": 6,
        "losses": 3,
        "PF": 1947.5,
        "playoff_odds": 83.77,
        "seeds": [
            6.1,
            21.0,
            19.25,
            15.58,
            12.38,
            9.46,
            6.83,
            4.52,
            2.83,
            1.41,
            0.46,
            0.14,
            0.03,
            0.0
        ],
        "records": {
            "12-0": {
                "made_playoffs": 75,
                "total": 75,
                "odds": 100.0
            },
            "11-1": {
                "made_playoffs": 797,
                "total": 797,
                "odds": 100.0
            },
            "10-2": {
                "made_playoffs": 3552,
                "total": 3552,
                "odds": 100.0
            },
            "9-3": {
                "made_playoffs": 9704,
                "total": 9704,
                "odds": 100.0
            },
            "8-4": {
                "made_playoffs": 17500,
                "total": 17500,
                "odds": 100.0
            },
            "7-5": {
                "made_playoffs": 22721,
                "total": 22733,
                "odds": 99.95
            },
            "6-6": {
                "made_playoffs": 20405,
                "total": 21155,
                "odds": 96.45
            },
            "5-7": {
                "made_playoffs": 8526,
                "total": 14462,
                "odds": 58.95
            },
            "4-8": {
                "made_playoffs": 487,
                "total": 7001,
                "odds": 6.96
            },
            "3-9": {
                "made_playoffs": 3,
                "total": 2388,
                "odds": 0.13
            },
            "2-10": {
                "made_playoffs": 0,
                "total": 558,
                "odds": 0.0
            },
            "1-11": {
                "made_playoffs": 0,
                "total": 72,
                "odds": 0.0
            },
            "0-12": {
                "made_playoffs": 0,
                "total": 3,
                "odds": 0.0
            }
        },
        "current_week": {
            "win": {
                "make_playoffs": 51683,
                "total": 57502,
                "odds": 89.88
            },
            "loss": {
                "make_playoffs": 32087,
                "total": 42498,
                "odds": 75.5
            }
        },
        "PF_avg": 216.38888888888889
    },
    "63303": {
        "name": "Buenos Necas",
        "owner": "Jorikke",
        "wins": 6,
        "losses": 3,
        "PF": 1931.85,
        "playoff_odds": 85.3,
        "seeds": [
            6.26,
            23.55,
            19.61,
            15.17,
            11.9,
            8.81,
            6.24,
            4.17,
            2.43,
            1.23,
            0.44,
            0.15,
            0.03,
            0.0
        ],
        "records": {
            "12-0": {
                "made_playoffs": 130,
                "total": 130,
                "odds": 100.0
            },
            "11-1": {
                "made_playoffs": 1084,
                "total": 1084,
                "odds": 100.0
            },
            "10-2": {
                "made_playoffs": 4556,
                "total": 4556,
                "odds": 100.0
            },
            "9-3": {
                "made_playoffs": 11569,
                "total": 11569,
                "odds": 100.0
            },
            "8-4": {
                "made_playoffs": 19251,
                "total": 19251,
                "odds": 100.0
            },
            "7-5": {
                "made_playoffs": 22976,
                "total": 23001,
                "odds": 99.89
            },
            "6-6": {
                "made_playoffs": 18788,
                "total": 19751,
                "odds": 95.12
            },
            "5-7": {
                "made_playoffs": 6626,
                "total": 12561,
                "odds": 52.75
            },
            "4-8": {
                "made_playoffs": 318,
                "total": 5709,
                "odds": 5.57
            },
            "3-9": {
                "made_playoffs": 2,
                "total": 1906,
                "odds": 0.1
            },
            "2-10": {
                "made_playoffs": 0,
                "total": 426,
                "odds": 0.0
            },
            "1-11": {
                "made_playoffs": 0,
                "total": 51,
                "odds": 0.0
            },
            "0-12": {
                "made_playoffs": 0,
                "total": 5,
                "odds": 0.0
            }
        },
        "current_week": {
            "win": {
                "make_playoffs": 47934,
                "total": 52430,
                "odds": 91.42
            },
            "loss": {
                "make_playoffs": 37366,
                "total": 47570,
                "odds": 78.55
            }
        },
        "PF_avg": 214.64999999999998
    },
    "63155": {
        "name": "Rossi Balboa & co.",
        "owner": "DonPaita",
        "wins": 6,
        "losses": 3,
        "PF": 1902.8,
        "playoff_odds": 80.68,
        "seeds": [
            4.8,
            16.31,
            18.04,
            16.82,
            14.01,
            10.71,
            7.9,
            5.16,
            3.25,
            1.8,
            0.83,
            0.27,
            0.08,
            0.02
        ],
        "records": {
            "12-0": {
                "made_playoffs": 63,
                "total": 63,
                "odds": 100.0
            },
            "11-1": {
                "made_playoffs": 686,
                "total": 686,
                "odds": 100.0
            },
            "10-2": {
                "made_playoffs": 3175,
                "total": 3175,
                "odds": 100.0
            },
            "9-3": {
                "made_playoffs": 9152,
                "total": 9152,
                "odds": 100.0
            },
            "8-4": {
                "made_playoffs": 17142,
                "total": 17142,
                "odds": 100.0
            },
            "7-5": {
                "made_playoffs": 22575,
                "total": 22594,
                "odds": 99.92
            },
            "6-6": {
                "made_playoffs": 20180,
                "total": 21628,
                "odds": 93.3
            },
            "5-7": {
                "made_playoffs": 7257,
                "total": 14932,
                "odds": 48.6
            },
            "4-8": {
                "made_playoffs": 451,
                "total": 7282,
                "odds": 6.19
            },
            "3-9": {
                "made_playoffs": 2,
                "total": 2641,
                "odds": 0.08
            },
            "2-10": {
                "made_playoffs": 0,
                "total": 609,
                "odds": 0.0
            },
            "1-11": {
                "made_playoffs": 0,
                "total": 88,
                "odds": 0.0
            },
            "0-12": {
                "made_playoffs": 0,
                "total": 8,
                "odds": 0.0
            }
        },
        "current_week": {
            "win": {
                "make_playoffs": 47390,
                "total": 53985,
                "odds": 87.78
            },
            "loss": {
                "make_playoffs": 33293,
                "total": 46015,
                "odds": 72.35
            }
        },
        "PF_avg": 211.42222222222222
    },
    "63133": {
        "name": "Demi dovado",
        "owner": "Postyyy",
        "wins": 6,
        "losses": 3,
        "PF": 1852.9,
        "playoff_odds": 66.67,
        "seeds": [
            2.61,
            8.6,
            12.0,
            14.13,
            14.95,
            14.37,
            11.95,
            8.95,
            6.1,
            3.53,
            1.73,
            0.74,
            0.27,
            0.08
        ],
        "records": {
            "12-0": {
                "made_playoffs": 23,
                "total": 23,
                "odds": 100.0
            },
            "11-1": {
                "made_playoffs": 231,
                "total": 231,
                "odds": 100.0
            },
            "10-2": {
                "made_playoffs": 1468,
                "total": 1468,
                "odds": 100.0
            },
            "9-3": {
                "made_playoffs": 5365,
                "total": 5365,
                "odds": 100.0
            },
            "8-4": {
                "made_playoffs": 12113,
                "total": 12113,
                "odds": 100.0
            },
            "7-5": {
                "made_playoffs": 19761,
                "total": 19825,
                "odds": 99.68
            },
            "6-6": {
                "made_playoffs": 20249,
                "total": 23201,
                "odds": 87.28
            },
            "5-7": {
                "made_playoffs": 7087,
                "total": 19502,
                "odds": 36.34
            },
            "4-8": {
                "made_playoffs": 368,
                "total": 11747,
                "odds": 3.13
            },
            "3-9": {
                "made_playoffs": 0,
                "total": 4866,
                "odds": 0.0
            },
            "2-10": {
                "made_playoffs": 0,
                "total": 1414,
                "odds": 0.0
            },
            "1-11": {
                "made_playoffs": 0,
                "total": 222,
                "odds": 0.0
            },
            "0-12": {
                "made_playoffs": 0,
                "total": 23,
                "odds": 0.0
            }
        },
        "current_week": {
            "win": {
                "make_playoffs": 33413,
                "total": 42498,
                "odds": 78.62
            },
            "loss": {
                "make_playoffs": 33252,
                "total": 57502,
                "odds": 57.83
            }
        },
        "PF_avg": 205.8777777777778
    },
    "63384": {
        "name": "All Cats Are Beautiful",
        "owner": "ALittleLion",
        "wins": 6,
        "losses": 3,
        "PF": 1847.7,
        "playoff_odds": 66.49,
        "seeds": [
            2.2,
            9.94,
            12.61,
            14.18,
            14.21,
            13.34,
            11.52,
            8.82,
            6.26,
            3.91,
            1.97,
            0.74,
            0.25,
            0.05
        ],
        "records": {
            "12-0": {
                "made_playoffs": 21,
                "total": 21,
                "odds": 100.0
            },
            "11-1": {
                "made_playoffs": 342,
                "total": 342,
                "odds": 100.0
            },
            "10-2": {
                "made_playoffs": 1834,
                "total": 1834,
                "odds": 100.0
            },
            "9-3": {
                "made_playoffs": 5768,
                "total": 5768,
                "odds": 100.0
            },
            "8-4": {
                "made_playoffs": 12933,
                "total": 12934,
                "odds": 99.99
            },
            "7-5": {
                "made_playoffs": 19977,
                "total": 20057,
                "odds": 99.6
            },
            "6-6": {
                "made_playoffs": 19300,
                "total": 22495,
                "odds": 85.8
            },
            "5-7": {
                "made_playoffs": 6040,
                "total": 18901,
                "odds": 31.96
            },
            "4-8": {
                "made_playoffs": 271,
                "total": 11283,
                "odds": 2.4
            },
            "3-9": {
                "made_playoffs": 1,
                "total": 4771,
                "odds": 0.02
            },
            "2-10": {
                "made_playoffs": 0,
                "total": 1347,
                "odds": 0.0
            },
            "1-11": {
                "made_playoffs": 0,
                "total": 230,
                "odds": 0.0
            },
            "0-12": {
                "made_playoffs": 0,
                "total": 17,
                "odds": 0.0
            }
        },
        "current_week": {
            "win": {
                "make_playoffs": 40189,
                "total": 52444,
                "odds": 76.63
            },
            "loss": {
                "make_playoffs": 26298,
                "total": 47556,
                "odds": 55.3
            }
        },
        "PF_avg": 205.3
    },
    "63154": {
        "name": "East Coast Bias",
        "owner": "ashdc",
        "wins": 5,
        "losses": 4,
        "PF": 1814.85,
        "playoff_odds": 30.59,
        "seeds": [
            0.27,
            2.17,
            3.83,
            5.89,
            7.96,
            10.47,
            12.86,
            14.83,
            14.34,
            12.83,
            8.0,
            4.22,
            1.81,
            0.52
        ],
        "records": {
            "12-0": {
                "made_playoffs": 3,
                "total": 3,
                "odds": 100.0
            },
            "11-1": {
                "made_playoffs": 112,
                "total": 112,
                "odds": 100.0
            },
            "10-2": {
                "made_playoffs": 674,
                "total": 674,
                "odds": 100.0
            },
            "9-3": {
                "made_playoffs": 2862,
                "total": 2862,
                "odds": 100.0
            },
            "8-4": {
                "made_playoffs": 8101,
                "total": 8139,
                "odds": 99.53
            },
            "7-5": {
                "made_playoffs": 12860,
                "total": 15494,
                "odds": 83.0
            },
            "6-6": {
                "made_playoffs": 5584,
                "total": 21708,
                "odds": 25.72
            },
            "5-7": {
                "made_playoffs": 392,
                "total": 22020,
                "odds": 1.78
            },
            "4-8": {
                "made_playoffs": 2,
                "total": 16484,
                "odds": 0.01
            },
            "3-9": {
                "made_playoffs": 0,
                "total": 8776,
                "odds": 0.0
            },
            "2-10": {
                "made_playoffs": 0,
                "total": 3031,
                "odds": 0.0
            },
            "1-11": {
                "made_playoffs": 0,
                "total": 634,
                "odds": 0.0
            },
            "0-12": {
                "made_playoffs": 0,
                "total": 63,
                "odds": 0.0
            }
        },
        "current_week": {
            "win": {
                "make_playoffs": 19690,
                "total": 47556,
                "odds": 41.4
            },
            "loss": {
                "make_playoffs": 10900,
                "total": 52444,
                "odds": 20.78
            }
        },
        "PF_avg": 201.64999999999998
    },
    "63158": {
        "name": "I'm Bettman",
        "owner": "CDawg614",
        "wins": 4,
        "losses": 5,
        "PF": 1899.9,
        "playoff_odds": 40.27,
        "seeds": [
            0.4,
            2.75,
            5.34,
            8.06,
            10.73,
            12.99,
            14.43,
            14.06,
            12.13,
            8.99,
            5.54,
            2.84,
            1.3,
            0.44
        ],
        "records": {
            "12-0": {
                "made_playoffs": 57,
                "total": 57,
                "odds": 100.0
            },
            "11-1": {
                "made_playoffs": 564,
                "total": 564,
                "odds": 100.0
            },
            "10-2": {
                "made_playoffs": 2976,
                "total": 2976,
                "odds": 100.0
            },
            "9-3": {
                "made_playoffs": 8417,
                "total": 8424,
                "odds": 99.92
            },
            "8-4": {
                "made_playoffs": 15285,
                "total": 16283,
                "odds": 93.87
            },
            "7-5": {
                "made_playoffs": 11541,
                "total": 22221,
                "odds": 51.94
            },
            "6-6": {
                "made_playoffs": 1419,
                "total": 22021,
                "odds": 6.44
            },
            "5-7": {
                "made_playoffs": 7,
                "total": 15645,
                "odds": 0.04
            },
            "4-8": {
                "made_playoffs": 0,
                "total": 8083,
                "odds": 0.0
            },
            "3-9": {
                "made_playoffs": 0,
                "total": 2912,
                "odds": 0.0
            },
            "2-10": {
                "made_playoffs": 0,
                "total": 705,
                "odds": 0.0
            },
            "1-11": {
                "made_playoffs": 0,
                "total": 102,
                "odds": 0.0
            },
            "0-12": {
                "made_playoffs": 0,
                "total": 7,
                "odds": 0.0
            }
        },
        "current_week": {
            "win": {
                "make_playoffs": 24625,
                "total": 47570,
                "odds": 51.77
            },
            "loss": {
                "make_playoffs": 15641,
                "total": 52430,
                "odds": 29.83
            }
        },
        "PF_avg": 211.10000000000002
    },
    "63171": {
        "name": "Celebring It On Back Now",
        "owner": "SPEMason",
        "wins": 4,
        "losses": 5,
        "PF": 1838.6,
        "playoff_odds": 24.09,
        "seeds": [
            0.11,
            1.06,
            2.54,
            4.56,
            6.69,
            9.13,
            11.81,
            14.15,
            15.46,
            14.54,
            9.95,
            5.8,
            3.09,
            1.1
        ],
        "records": {
            "12-0": {
                "made_playoffs": 17,
                "total": 17,
                "odds": 100.0
            },
            "11-1": {
                "made_playoffs": 212,
                "total": 212,
                "odds": 100.0
            },
            "10-2": {
                "made_playoffs": 1431,
                "total": 1431,
                "odds": 100.0
            },
            "9-3": {
                "made_playoffs": 4871,
                "total": 4887,
                "odds": 99.67
            },
            "8-4": {
                "made_playoffs": 10212,
                "total": 11657,
                "odds": 87.6
            },
            "7-5": {
                "made_playoffs": 6730,
                "total": 18908,
                "odds": 35.59
            },
            "6-6": {
                "made_playoffs": 614,
                "total": 22790,
                "odds": 2.69
            },
            "5-7": {
                "made_playoffs": 1,
                "total": 19921,
                "odds": 0.01
            },
            "4-8": {
                "made_playoffs": 0,
                "total": 12496,
                "odds": 0.0
            },
            "3-9": {
                "made_playoffs": 0,
                "total": 5662,
                "odds": 0.0
            },
            "2-10": {
                "made_playoffs": 0,
                "total": 1662,
                "odds": 0.0
            },
            "1-11": {
                "made_playoffs": 0,
                "total": 325,
                "odds": 0.0
            },
            "0-12": {
                "made_playoffs": 0,
                "total": 32,
                "odds": 0.0
            }
        },
        "current_week": {
            "win": {
                "make_playoffs": 17820,
                "total": 58316,
                "odds": 30.56
            },
            "loss": {
                "make_playoffs": 6268,
                "total": 41684,
                "odds": 15.04
            }
        },
        "PF_avg": 204.2888888888889
    },
    "63325": {
        "name": "the H\u00f6gamaniacs",
        "owner": "yoshirider2136",
        "wins": 3,
        "losses": 6,
        "PF": 1853.95,
        "playoff_odds": 16.13,
        "seeds": [
            0.04,
            0.61,
            1.49,
            2.65,
            4.54,
            6.8,
            9.78,
            13.24,
            16.3,
            16.41,
            12.16,
            8.36,
            5.1,
            2.51
        ],
        "records": {
            "12-0": {
                "made_playoffs": 41,
                "total": 41,
                "odds": 100.0
            },
            "11-1": {
                "made_playoffs": 514,
                "total": 514,
                "odds": 100.0
            },
            "10-2": {
                "made_playoffs": 2308,
                "total": 2313,
                "odds": 99.78
            },
            "9-3": {
                "made_playoffs": 6437,
                "total": 7133,
                "odds": 90.24
            },
            "8-4": {
                "made_playoffs": 6038,
                "total": 14860,
                "odds": 40.63
            },
            "7-5": {
                "made_playoffs": 783,
                "total": 21211,
                "odds": 3.69
            },
            "6-6": {
                "made_playoffs": 9,
                "total": 22435,
                "odds": 0.04
            },
            "5-7": {
                "made_playoffs": 0,
                "total": 16966,
                "odds": 0.0
            },
            "4-8": {
                "made_playoffs": 0,
                "total": 9654,
                "odds": 0.0
            },
            "3-9": {
                "made_playoffs": 0,
                "total": 3699,
                "odds": 0.0
            },
            "2-10": {
                "made_playoffs": 0,
                "total": 1018,
                "odds": 0.0
            },
            "1-11": {
                "made_playoffs": 0,
                "total": 146,
                "odds": 0.0
            },
            "0-12": {
                "made_playoffs": 0,
                "total": 10,
                "odds": 0.0
            }
        },
        "current_week": {
            "win": {
                "make_playoffs": 10975,
                "total": 46015,
                "odds": 23.85
            },
            "loss": {
                "make_playoffs": 5155,
                "total": 53985,
                "odds": 9.55
            }
        },
        "PF_avg": 205.99444444444444
    },
    "63139": {
        "name": "O Brother, Where Art Ross?",
        "owner": "Khaki_Scout",
        "wins": 3,
        "losses": 6,
        "PF": 1786.35,
        "playoff_odds": 3.56,
        "seeds": [
            0.01,
            0.05,
            0.2,
            0.46,
            0.95,
            1.89,
            3.23,
            5.45,
            8.71,
            13.53,
            20.39,
            19.83,
            15.68,
            9.61
        ],
        "records": {
            "12-0": {
                "made_playoffs": 2,
                "total": 2,
                "odds": 100.0
            },
            "11-1": {
                "made_playoffs": 34,
                "total": 34,
                "odds": 100.0
            },
            "10-2": {
                "made_playoffs": 279,
                "total": 279,
                "odds": 100.0
            },
            "9-3": {
                "made_playoffs": 1332,
                "total": 1497,
                "odds": 88.98
            },
            "8-4": {
                "made_playoffs": 1643,
                "total": 4894,
                "odds": 33.57
            },
            "7-5": {
                "made_playoffs": 264,
                "total": 11226,
                "odds": 2.35
            },
            "6-6": {
                "made_playoffs": 4,
                "total": 18821,
                "odds": 0.02
            },
            "5-7": {
                "made_playoffs": 0,
                "total": 23017,
                "odds": 0.0
            },
            "4-8": {
                "made_playoffs": 0,
                "total": 20409,
                "odds": 0.0
            },
            "3-9": {
                "made_playoffs": 0,
                "total": 12874,
                "odds": 0.0
            },
            "2-10": {
                "made_playoffs": 0,
                "total": 5403,
                "odds": 0.0
            },
            "1-11": {
                "made_playoffs": 0,
                "total": 1396,
                "odds": 0.0
            },
            "0-12": {
                "made_playoffs": 0,
                "total": 148,
                "odds": 0.0
            }
        },
        "current_week": {
            "win": {
                "make_playoffs": 2794,
                "total": 53772,
                "odds": 5.2
            },
            "loss": {
                "make_playoffs": 764,
                "total": 46228,
                "odds": 1.65
            }
        },
        "PF_avg": 198.48333333333332
    },
    "63141": {
        "name": "Bert and Erne",
        "owner": "Howe_U_Doin",
        "wins": 3,
        "losses": 6,
        "PF": 1734.0,
        "playoff_odds": 1.45,
        "seeds": [
            0.0,
            0.01,
            0.05,
            0.19,
            0.36,
            0.84,
            1.58,
            3.16,
            5.59,
            9.54,
            15.84,
            21.55,
            23.0,
            18.3
        ],
        "records": {
            "11-1": {
                "made_playoffs": 13,
                "total": 13,
                "odds": 100.0
            },
            "10-2": {
                "made_playoffs": 117,
                "total": 118,
                "odds": 99.15
            },
            "9-3": {
                "made_playoffs": 582,
                "total": 709,
                "odds": 82.09
            },
            "8-4": {
                "made_playoffs": 667,
                "total": 2762,
                "odds": 24.15
            },
            "7-5": {
                "made_playoffs": 70,
                "total": 7599,
                "odds": 0.92
            },
            "6-6": {
                "made_playoffs": 0,
                "total": 15094,
                "odds": 0.0
            },
            "5-7": {
                "made_playoffs": 0,
                "total": 22364,
                "odds": 0.0
            },
            "4-8": {
                "made_playoffs": 0,
                "total": 22950,
                "odds": 0.0
            },
            "3-9": {
                "made_playoffs": 0,
                "total": 17071,
                "odds": 0.0
            },
            "2-10": {
                "made_playoffs": 0,
                "total": 8468,
                "odds": 0.0
            },
            "1-11": {
                "made_playoffs": 0,
                "total": 2501,
                "odds": 0.0
            },
            "0-12": {
                "made_playoffs": 0,
                "total": 351,
                "odds": 0.0
            }
        },
        "current_week": {
            "win": {
                "make_playoffs": 1103,
                "total": 41684,
                "odds": 2.65
            },
            "loss": {
                "make_playoffs": 346,
                "total": 58316,
                "odds": 0.59
            }
        },
        "PF_avg": 192.66666666666666
    },
    "63134": {
        "name": "Hellbuycky Barnes",
        "owner": "Degradation",
        "wins": 2,
        "losses": 7,
        "PF": 1737.8,
        "playoff_odds": 0.87,
        "seeds": [
            0.0,
            0.0,
            0.03,
            0.08,
            0.25,
            0.51,
            1.1,
            2.25,
            4.04,
            7.24,
            13.31,
            18.96,
            23.85,
            28.38
        ],
        "records": {
            "12-0": {
                "made_playoffs": 3,
                "total": 3,
                "odds": 100.0
            },
            "11-1": {
                "made_playoffs": 41,
                "total": 41,
                "odds": 100.0
            },
            "10-2": {
                "made_playoffs": 290,
                "total": 330,
                "odds": 87.88
            },
            "9-3": {
                "made_playoffs": 456,
                "total": 1472,
                "odds": 30.98
            },
            "8-4": {
                "made_playoffs": 84,
                "total": 4930,
                "odds": 1.7
            },
            "7-5": {
                "made_playoffs": 0,
                "total": 11235,
                "odds": 0.0
            },
            "6-6": {
                "made_playoffs": 0,
                "total": 18974,
                "odds": 0.0
            },
            "5-7": {
                "made_playoffs": 0,
                "total": 22936,
                "odds": 0.0
            },
            "4-8": {
                "made_playoffs": 0,
                "total": 20251,
                "odds": 0.0
            },
            "3-9": {
                "made_playoffs": 0,
                "total": 12805,
                "odds": 0.0
            },
            "2-10": {
                "made_playoffs": 0,
                "total": 5443,
                "odds": 0.0
            },
            "1-11": {
                "made_playoffs": 0,
                "total": 1414,
                "odds": 0.0
            },
            "0-12": {
                "made_playoffs": 0,
                "total": 166,
                "odds": 0.0
            }
        },
        "current_week": {
            "win": {
                "make_playoffs": 706,
                "total": 46228,
                "odds": 1.53
            },
            "loss": {
                "make_playoffs": 168,
                "total": 53772,
                "odds": 0.31
            }
        },
        "PF_avg": 193.08888888888887
    },
    "63214": {
        "name": "The Brady Bunch",
        "owner": "khansense",
        "wins": 2,
        "losses": 7,
        "PF": 1718.75,
        "playoff_odds": 0.42,
        "seeds": [
            0.0,
            0.0,
            0.01,
            0.03,
            0.11,
            0.27,
            0.58,
            1.19,
            2.55,
            5.03,
            9.37,
            16.38,
            25.5,
            38.99
        ],
        "records": {
            "11-1": {
                "made_playoffs": 14,
                "total": 14,
                "odds": 100.0
            },
            "10-2": {
                "made_playoffs": 121,
                "total": 155,
                "odds": 78.06
            },
            "9-3": {
                "made_playoffs": 240,
                "total": 749,
                "odds": 32.04
            },
            "8-4": {
                "made_playoffs": 41,
                "total": 3016,
                "odds": 1.36
            },
            "7-5": {
                "made_playoffs": 0,
                "total": 8036,
                "odds": 0.0
            },
            "6-6": {
                "made_playoffs": 0,
                "total": 15482,
                "odds": 0.0
            },
            "5-7": {
                "made_playoffs": 0,
                "total": 22220,
                "odds": 0.0
            },
            "4-8": {
                "made_playoffs": 0,
                "total": 22801,
                "odds": 0.0
            },
            "3-9": {
                "made_playoffs": 0,
                "total": 16702,
                "odds": 0.0
            },
            "2-10": {
                "made_playoffs": 0,
                "total": 8144,
                "odds": 0.0
            },
            "1-11": {
                "made_playoffs": 0,
                "total": 2383,
                "odds": 0.0
            },
            "0-12": {
                "made_playoffs": 0,
                "total": 298,
                "odds": 0.0
            }
        },
        "current_week": {
            "win": {
                "make_playoffs": 245,
                "total": 22209,
                "odds": 1.1
            },
            "loss": {
                "make_playoffs": 171,
                "total": 77791,
                "odds": 0.22
            }
        },
        "PF_avg": 190.97222222222223
    }
}